lissajous/__init__.py
lissajous/__main__.py
lissajous-0.1.3.post1.dist-info/entry_points.txt
lissajous-0.1.3.post1.dist-info/LICENSE
lissajous-0.1.3.post1.dist-info/WHEEL
lissajous-0.1.3.post1.dist-info/METADATA
lissajous-0.1.3.post1.dist-info/RECORD
