Metadata-Version: 2.1
Name: lissajous
Version: 0.1.3.post1
Summary: A Lissajous Curve Visualizer written in Python
Home-page: https://github.com/kosayoda/lissajous
License: MIT
Keywords: lissajous,visualizer,visualiser
Author: kosayoda
Author-email: kieransiek@gmail.com
Requires-Python: >=3.6,<4.0
Classifier: License :: OSI Approved :: MIT License
Classifier: Programming Language :: Python :: 3
Classifier: Programming Language :: Python :: 3.6
Classifier: Programming Language :: Python :: 3.7
Requires-Dist: matplotlib (>=3.0,<4.0)
Requires-Dist: numpy (>=1.16,<2.0)
Project-URL: Repository, https://github.com/kosayoda/lissajous
